nuclei_discovery/__init__.py
nuclei_discovery/ckpt.py
nuclei_discovery/config.py
nuclei_discovery/config_default.ini
nuclei_discovery/crop.py
nuclei_discovery/dataset.py
nuclei_discovery/distribution.py
nuclei_discovery/helper.py
nuclei_discovery/loss.py
nuclei_discovery/model.py
nuclei_discovery/scan_miss.py
nuclei_discovery/split.py
nuclei_discovery/stitch_patch.py
nuclei_discovery/train.py
nuclei_discovery/valid.py
nuclei_discovery/version.py
nuclei_discovery-1.0.22.dist-info/METADATA
nuclei_discovery-1.0.22.dist-info/WHEEL
nuclei_discovery-1.0.22.dist-info/top_level.txt
nuclei_discovery-1.0.22.dist-info/RECORD
