Metadata-Version: 2.1
Name: nuclei-discovery
Version: 1.0.22
Summary: Nuclei Discovery
Home-page: http://www.aixmed.com
Author: Jimmy Lee
Author-email: jimmy.lee@aixmed.com
License: © 2018 AIxMed, Inc. All Rights Reserved
Platform: UNKNOWN
Requires-Dist: numpy (>=1.14)
Requires-Dist: matplotlib (>=2.1)
Requires-Dist: Scipy (>=0.19)
Requires-Dist: scikit-image (==0.13.1)
Requires-Dist: pandas (>=0.20)
Requires-Dist: Pillow (>=5.0)
Requires-Dist: tensorboardX (>=1.1)
Requires-Dist: tqdm (>=4.0)
Requires-Dist: scikit-learn (>=0.19)
